chord/__init__.py
plotapi/__init__.py
chord-6.0.1.dist-info/LICENSE
chord-6.0.1.dist-info/METADATA
chord-6.0.1.dist-info/WHEEL
chord-6.0.1.dist-info/top_level.txt
chord-6.0.1.dist-info/RECORD
