Metadata-Version: 2.1
Name: chord
Version: 6.0.1
Summary: Engaging visualisations, made easy.
Home-page: https://plotapi.com
Author: Dr. Shahin Rostami
Author-email: hello@plotapi.com
License: MIT
Platform: UNKNOWN
